video_sampler/__init__.py
video_sampler/__main__.py
video_sampler/buffer.py
video_sampler/config.py
video_sampler/gating.py
video_sampler/iterators.py
video_sampler/logging.py
video_sampler/schemas.py
video_sampler/ttl_counter.py
video_sampler/utils.py
video_sampler/worker.py
video_sampler/integrations/__init__.py
video_sampler/integrations/llava_chat.py
video_sampler/integrations/yt_dlp_plugin.py
video_sampler/language/__init__.py
video_sampler/language/keyword_capture.py
video_sampler/samplers/__init__.py
video_sampler/samplers/base_sampler.py
video_sampler/samplers/gpu_sampler.py
video_sampler/samplers/image_sampler.py
video_sampler/samplers/video_sampler.py
video_sampler/visualisation/__init__.py
video_sampler/visualisation/clustering.py
video_sampler-0.13.0.dist-info/entry_points.txt
video_sampler-0.13.0.dist-info/LICENSE
video_sampler-0.13.0.dist-info/WHEEL
video_sampler-0.13.0.dist-info/METADATA
video_sampler-0.13.0.dist-info/RECORD
