Metadata-Version: 2.3
Name: video_sampler
Version: 0.13.0
Summary: Video Sampler -- sample frames from a video file
Keywords: video sampling,frame selection,labelling,labeling,annotation
Author-email: LemurPwned <lemurpwned@gmail.com>
Requires-Python: >3.9
Classifier: Development Status :: 3 - Alpha
Classifier: License :: OSI Approved :: MIT License
Classifier: Natural Language :: English
Classifier: Operating System :: OS Independent
Classifier: Programming Language :: Python
Classifier: Programming Language :: Python :: 3.8
Classifier: Programming Language :: Python :: 3.9
Requires-Dist: av >=13.0.0
Requires-Dist: ImageHash >=4.3.1
Requires-Dist: Pillow >=10.0.0
Requires-Dist: rich >= 13.5.3
Requires-Dist: typer >= 0.12.5
Requires-Dist: tqdm >= 4.66.1
Requires-Dist: opencv-python-headless >= 4.9.0.80
Requires-Dist: pydantic >= 2.6.1
Requires-Dist: pyaml >= 6.0.1
Requires-Dist: requests >= 2.31.0
Requires-Dist: open_clip_torch >= 2.23.0 ; extra == "all"
Requires-Dist: torch >= 2.1.0 ; extra == "all"
Requires-Dist: yt-dlp >= 2023.12.30 ; extra == "all"
Requires-Dist: spacy >= 3.7.0 ; extra == "all"
Requires-Dist: pysrt >= 1.1.2 ; extra == "all"
Requires-Dist: openai >= 1.16.2 ; extra == "all"
Requires-Dist: open_clip_torch >= 2.23.0 ; extra == "clip"
Requires-Dist: torch >= 2.1.0 ; extra == "clip"
Requires-Dist: pre-commit ; extra == "dev"
Requires-Dist: bump2version ; extra == "dev"
Requires-Dist: tabulate ; extra == "dev"
Requires-Dist: pytest ; extra == "dev"
Requires-Dist: pycuda >= 2024.1.2 ; extra == "gpu"
Requires-Dist: PyNvVideoCodec >= 1.0.2 ; extra == "gpu"
Requires-Dist: spacy >= 3.7.0 ; extra == "language"
Requires-Dist: pysrt >= 1.1.2 ; extra == "language"
Requires-Dist: yt-dlp >= 2023.12.30 ; extra == "ytdlp"
Project-URL: Source, https://github.com/LemurPwned/video-sampler
Provides-Extra: all
Provides-Extra: clip
Provides-Extra: dev
Provides-Extra: gpu
Provides-Extra: language
Provides-Extra: ytdlp
